{
  "deployment_id": "DEPLOY-20251026-151509",
  "started_at": "2025-10-26T15:15:09.661269",
  "infrastructure": {
    "status": "success",
    "components": {
      "s3_data_lake": "deployed",
      "glue_catalog": "deployed"
    },
    "metadata": {
      "bucket_name": "dynamic-pricing-data-lake",
      "region": "us-east-1",
      "created_at": "2025-10-26T15:15:17.219760",
      "status": "active"
    },
    "deployed_at": "2025-10-26T15:15:17.219768"
  },
  "ai_model": {
    "status": "success",
    "metrics": {
      "mse": 5.030769042640303,
      "rmse": 2.2429375922304,
      "r2_score": 0.9934112795463296,
      "trained_at": "2025-10-26T15:15:18.650404"
    },
    "feature_importance": {
      "base_price": 0.9605116840745463,
      "demand": 0.034686373963355915,
      "competition_price": 0.0033869544513935976,
      "time_of_day": 0.000993222264955181,
      "day_of_week": 0.00025376810622603814,
      "season": 0.00016799713952302667
    },
    "trained_at": "2025-10-26T15:15:18.691155"
  },
  "data_pipeline": {
    "status": "success",
    "records_processed": 3000,
    "validation": {
      "total_records": 3000,
      "missing_values": {
        "product_id": 0,
        "timestamp": 0,
        "base_price": 0,
        "current_price": 0,
        "demand": 0,
        "competition_price": 0,
        "time_of_day": 0,
        "day_of_week": 0,
        "season": 0
      },
      "duplicate_records": 